README.md
setup.py
micropython_senko.egg-info/PKG-INFO
micropython_senko.egg-info/SOURCES.txt
micropython_senko.egg-info/dependency_links.txt
micropython_senko.egg-info/top_level.txt
senko/senko.py