Metadata-Version: 1.0
Name: micropython-senko
Version: 2.0.1
Summary: Simplest OTA update solution for your Micropython projects.
Home-page: https://github.com/RangerDigital/senko
Author: Jakub Bednarski
Author-email: Jakub@Bednarski.dev
License: UNKNOWN
Platform: UNKNOWN
